Workbook

Sheet Начни здесь
B1: КАК ЗАПОЛНЯТЬ (обновлено 20.10.2026)
B2: Работаем по очереди: один человек → одно сообщение в чат. Пока ты собираешь следующего, я переписываю реплики уже присланного.
A3: 1 | B3: Лист «Персонажи», колонка X «★ Что сделать» — красные строки. Чаще всего нужно только дописать отчество (в колонке N стоит «Отчество?»).
A4: 2 | B4: ФИО я уже переставил по правилу: имя и отчество настоящие, фамилия настоящая только если она одна в деле (или родство есть и в сюжете — Кирилл и Марина). Старое ФИО — в колонке Y. Не согласен с фамилией — просто впиши свою.
A5: 3 | B5: Возраст в игре — поставил числа из сценария (колонка O). Твоё «в жизни N» перенёс в «Заметки». Хочешь другой — меняй число.
A6: 4 | B6: Скрины переписок — прямо в чат, картинками. Первой строкой: «Кто: Кирилл (дядя)». 3–6 скринов, видны его/её сообщения в разных ситуациях: короткий ответ, длинный рассказ, эмоция, приветствие/прощание.
A7: 5 | B7: Можно вместо скринов скопировать 10–15 сообщений текстом — так точнее видно точки и смайлы. Номера и чужие личные темы можно закрасить.
A8: 6 | B8: Скрины и дословные цитаты в игру не попадут — я записываю только манеру («точки в конце, 👌, говорит быстро»).
A9: 7 | B9: Лист «Скрины и фото» — что прислать по каждому человеку. Отмечай «Отправлено».
A10: 8 | B10: Таблицу целиком присылай, когда допишешь отчества, — я сразу подставлю имена во все документы.
B11: Порядок, в котором удобнее присылать: Кирилл → ты (Воронцов) → Слава (Волков) → Алина (Марина) → дедушка (Завьялов) → Юля (Громова) → остальные.
B12: Решения 20.10: Марина — дочь Кирилла и крестница Воронцова; привычка Кирилла — «Было бы за что»; одинаковые фамилии в деле разведены.

Sheet Инструкция
A1: За кулисами правды — карта персонажей
A2: Версия сюжета от 11.10.2026: премьера 10 ноября, таблетки вместо ингалятора, побег поездом 23:40, одна развязка.
A4: Что заполнить
A5: 1. Лист «Персонажи», жёлтые колонки M–V. Сначала 5 ключевых ролей (розовые), потом остальные.
A6: 2. Колонка L «★ Что важно заполнить» подсказывает, без чего нельзя писать документы именно для этой роли.
A7: 3. Лист «Участие» сам подтянет имена и покажет, кому из родственников что нужно сделать: фото, видео, голос, переписка.
A8: 4. Лист «Фоновые имена» — люди, которые только упоминаются в документах. Можно вписать родственников, которым не досталось роли.
A10: Настоящие имена
A11: • Колонка N «ФИО в документах» — ровно так, как будет напечатано в протоколах: Фамилия Имя Отчество.
A12: • Если у нескольких родственников общая фамилия, лучше дать им разные (настоящие девичьи или вымышленные). Иначе протоколы будут путать игроков.
A13: • Пол персонажа подстраивается под родственника, тексты я перепишу под него. Жёстких ограничений два: Волков на 15+ лет моложе Воронцова; Марина — дочь Кирилла и крестница Воронцова (решение 20.10).
A14: • Рабочие имена (Воронцов, Завьялов…) останутся только как обозначение роли в сценарии.
... A36: Розовый — ключевая роль · Жёлтый — заполняешь ты · Серый — пример или служебная роль · Красная заливка в колонке M — ключевая роль ещё без родственника.

Sheet Скрины и фото
A1: Очередь | B1: Роль | C1: Кто в жизни | D1: Скрины / текст (манера) | E1: Фото / видео / голос (позже) | F1: Отправлено?
A2: 1 | B2: Кирилл | C2: =IF(Персонажи!M8="","—",Персонажи!M8) | D2: Скрины его сообщений: как пишет, «лимон», «вахуе» и т. п. | E2: Портрет. Голос анонимного звонка 45–60 с (текст дам)
A3: 2 | B3: Иван Воронцов | C3: =IF(Персонажи!M4="","—",Персонажи!M4) | D3: Твои скрины (скобки, абзацы, 😁 😭) + дружеское имя | E3: Портрет; в образе Арбенина; у кассы вокзала
A4: 3 | B4: Артём Волков | C4: =IF(Персонажи!M6="","—",Персонажи!M6) | D4: Скрины по желанию (манера уже есть) | E4: Портрет; видео-монолог 40–60 с днём у окна; у колонны на вокзале
A5: 4 | B5: Марина Тарасова | C5: =IF(Персонажи!M7="","—",Персонажи!M7) | D5: Скрины + как называет тебя | E5: Портрет
A6: 5 | B6: Юрий Завьялов | C6: =IF(Персонажи!M5="","—",Персонажи!M5) | D6: 1–2 фразы; скрины, если пишет | E6: Портрет; стол в кабинете
A7: 6 | B7: Михаил Громов | C7: =IF(Персонажи!M17="","—",Персонажи!M17) | D7: Скрины | E7: Портрет; «на совещании» (за окном лето)
A8: 7 | B8: Светлана Резникова | C8: =IF(Персонажи!M10="","—",Персонажи!M10) | D8: Фото маминых коротких пометок | E8: Портрет
A9: 8 | B9: Инна | C9: =IF(Персонажи!M14="","—",Персонажи!M14) | D9: Скрин подписей к постам | E9: Портрет; фото в броши; 8–11 фото для её страницы
A10: 9 | B10: Софья Вольская | C10: =IF(Персонажи!M16="","—",Персонажи!M16) | D10: Скрины | E10: Портрет
A11: 10 | B11: Стас Лёвин | C11: =IF(Персонажи!M9="","—",Персонажи!M9) | D11: 1–3 фразы, как рассказывает | E11: Портрет
A12: 11 | B12: Елена Гнедич | C12: =IF(Персонажи!M11="","—",Персонажи!M11) | D12: 1–3 ворчливые фразы | E12: Портрет
A13: 12 | B13: Олег Петрович | C13: =IF(Персонажи!M13="","—",Персонажи!M13) | D13: 1–2 фразы | E13: Портрет; 6–8 кадров у двери с сигаретой
A14: 13 | B14: Дмитрий | C14: =IF(Персонажи!M15="","—",Персонажи!M15) | D14: 1–2 фразы | E14: Портрет; за рулём
A15: 14 | B15: Виктор «Мастер» | C15: =IF(Персонажи!M12="","—",Персонажи!M12) | D15: 1–2 фразы | E15: Портрет
A16: 15 | B16: Майор Беляев | C16: =IF(Персонажи!M20="","—",Персонажи!M20) | D16: — (фразы уже есть) | E16: —

Sheet Персонажи
A1: СЦЕНАРИЙ — основа сюжета, менять не нужно | M1: ЗАПОЛНЯЕШЬ ТЫ | X1: ПОДСКАЗКИ (обновлено 20.10)
A2: № | B2: Роль (рабочее имя) | C2: Функция в сюжете | D2: Важность | E2: Пол и возраст | F2: Характер (основа) | G2: Где был 19:30–20:00 | H2: Первый опрос (этап 1): что говорит | I2: Что меняется позже | J2: Что скрывает | K2: Кого лучше ставить | L2: ★ Что важно заполнить | M2: Родственник (кто это в жизни) | N2: ФИО в документах | O2: Возраст в игре | P2: Фирменные фразы и словечки | Q2: Манера речи: темп, обращения, формальность | R2: Как пишет в мессенджере | S2: Жесты, привычки, внешние детали | T2: Семейные шутки и пасхалки | U2: Табу: что не трогать | V2: Готов сниматься? | W2: Заметки | X2: ★ Что сделать по строке | Y2: Было в «ФИО» до 20.10 (для сверки)
A3: — | B3: ПРИМЕР | C3: — | D3: — | E3: — | F3: — | G3: — | H3: — | I3: — | J3: — | K3: — | L3: — | M3: Дядя Коля | N3: Смирнов Николай Петрович | O3: 58 | P3: «Ну это к бабке не ходи», «Разберёмся» | Q3: Говорит медленно, всех зовёт по отчеству, любит паузы | R3: Только голосовые; если текстом — без точек и с «))» | S3: Звенит ключами, всё фотографирует на телефон, вечно в жилетке | T3: Каждое лето чинит одну и ту же лодку | U3: Не шутить про здоровье | V3: Да | W3: Если человек сильно моложе или старее (10-15 лет хотя бы) то можно будет с нейронкой омолодить/состарить его | X3: Красная — нужно что-то вписать; зелёная — строка готова.
A4: 1 | B4: Иван Воронцов | C4: Жертва. Звезда театра, ведущий подпольных аукционов, владелец архива | D4: Ключевой | E4: Лучше мужчина (играет Арбенина); 45–65 | F4: Харизматичный, гордый, привык к вниманию. Последний месяц нервный, оглядывается | G4: На сцене | H4: — (погиб). Говорит через переписку и письма | I4: Этап 3: переписка с Кириллом. Этап 4: облако — ультиматум Завьялову, обращение к тому, кто откроет архив. Развязка: письмо Марине | J4: Серьёзную астму; долю с аукционов наличными; архив и «мёртвую руку»; побег поездом в 23:40 | K4: Артистичного, кому понравится «эффектно умереть» и сняться в образе | L4: Как пишет в мессенджере (переписки с Кириллом, Вольской, Завьяловым). Фото в образе Арбенина. Как обращается к Марине | M4: я | N4: Молдованов Артём Сергеевич | O4: 56 | R4: со скобками пишет)) любит новые абзацы часто ставить, использует улыбающийся смайл во все зубы, плачущий сильно смайл тоже (могу потом прислать скрины, для всех остальных тоже) | S4: в очках всегда с прозрачной оправой, густые брови | T4: над бровями шутят, что якобы "Брежнев")) | U4: пофиг | V4: я хочу сгенерировать все видео, фото и тп (подскажи как лучше это сделать) | W4: я соберу скрины переписок, чтобы ты понимал как общаются люди, подскажи как лучше тебе это преподнести? / Возраст: в жизни мне 20, в игре все равно как поставить | X4: Фамилия одна в деле — оставил. «Артем» → «Артём». Впиши в «Заметки», как тебя зовут близкие друзья (Тёма? Артёмка?) — так тебя называет Кирилл в переписке. Скрины своих сообщений — пришли первым или вторым. | Y4: Молдованов Артем Сергеевич
A5: 2 | B5: Юрий Завьялов | C5: Худрук. Организатор убийства, председатель фонда «Сцена» | D5: Ключевой | E5: Любой; 50+, старше и главнее Волкова | F5: Властный, обаятельный на публике, холодный и расчётливый | G5: «Один в кабинете, работал с документами» — свидетелей нет | H5: Ссора в антракте «творческая, про бюджет декораций»; «уехал домой около десяти, сил не было» | I5: Показаний не меняет. Против него документы: рецепт Анаприлина, записка о камере, рабочий чат, смета, уход в 22:05 | J5: Аукционы и отмыв через фонд; организацию убийства; выбросил телефон Воронцова с моста | K5: Самого властного и харизматичного — того, кого «и так все слушаются» | L5: Манера речи (опрос, рабочий чат). Как пишет в мессенджере (ультиматум в облаке). Что «его» стоит на столе для фото кабинета | M5: мой дедушка | N5: Тарасов Николай Отчество? | O5: 61 | Q5: сдержаный, хорошо поставлена речь | W5: Возраст: 69 в жизни | X5: Нужно отчество дедушки. Фамилию Тарасов оставил только ему. Нужна 1–2 фразы дедушки и, если пишет в мессенджере, скрины. | Y5: Тарасов Николай (отчество забыл, потом заполню)
A6: 3 | B6: Артём Волков | C6: Дублёр Арбенина. Исполнитель: подменил таблетки, пытался войти в облако, забрал телефон | D6: Ключевой | E6: Любой; на 15+ лет моложе Воронцова | F6: Обаятельный, услужливый, амбициозный, «вне подозрений». В долгах | G6: «На 3-м этаже, репетировал» — свидетелей нет, показывает видео | H6: С 18:00 на 3-м этаже «на случай форс-мажора»; спустился «на шум» около 21:05; показывает видео с телефона | I6: Показаний не меняет. Ломается на этапе 4: дата видео, показания Гнедич, вокзальная камера, лог входа с его телефона. Развязка: признание | J6: Долг, закрытый через «декорации»; подсмотренный пароль; подмену таблеток; попытку взлома; кражу телефона | K6: Самого милого и «безобидного», с чувством юмора — на кого подумают последним | L6: Видео «репетиции»: 40–60 с монолога Арбенина, днём у окна. Фразы для опроса и признания | M6: муж сестры | N6: Блинов Вячеслав Отчество? | O6: 31 | Q6: доюродушный, улыбается часто, говорит достаточно быстро, вежливый | R6: ставит точки в конце предложения, начинает нове с той же строчки, использует смайлы (ОК жест рукой, смайл молитвы, иногда здоровается смайлом "машущая рука") | T6: много работает и из-за этого не попадает на семейные посиделки, шутят над его женой: даже не буду спрашивать, где славик, он все деньги мира пытается заработать | W6: Возраст: в жизни 32 | X6: Нужно отчество Славы. Фамилию Блинов оставил ему (у Громовой теперь другая). Манера есть. Скрины — по желанию. | Y6: Блинов Вячеслав
A7: 4 | B7: Марина Тарасова | C7: Крестница Воронцова и дочь Кирилла (решение 20.10). Своих детей у Воронцова нет — она ему вместо дочери | D7: Ключевой | E7: Женщина; около 24 в игре | F7: Подавленная, закрытая, защищает память мужа | G7: Дома, говорила по телефону с сестрой — сестра подтверждает | H7: «Последний месяц крёстный был не в себе, оглядывался»; «на сердце вроде не жаловался»; узнала от Завьялова, позвонила папе (Кириллу) | I7: Этап 2: признаёт астму крёстного, вскользь — «Седарин на ночь». Этап 4: признаёт, что он собирался уехать и звал её к себе; не сказала даже папе | J7: Астму крёстного; его побег (винит себя, что отпустила одного) | K7: Дочь того, кто играет Кирилла — фамилия и отчество совпадут | L7: Манера речи (три опроса). Как называет мужа. Ей адресовано письмо в развязке | M7: моя двоюродная сестра | N7: Горенкова Алина Александровна | O7: 24 | W7: Возраст: в жизни 15 | X7: Готово. По сюжету теперь дочь Кирилла и крестница Воронцова — фамилия и отчество совпадают с Кириллом сами. Нужны: манера речи, как зовёт тебя («дядя Тёма»?) — в «Заметки»; скрины. | Y7: Горенкова Алина Александровна
A8: 5 | B8: Кирилл | C8: Старый друг Воронцова со школы, отец Марины. Хранитель архива, анонимный звонивший | D8: Ключевой | E8: Любой; ровесник Воронцова | F8: Умный, скрытный, тревожный | G8: Дома, один — не подтверждено (в театр не входил) | H8: В шоке, отвечает односложно: «много виделись, вспоминали молодость». Речевой привычки здесь нет | I8: Этап 3: облако, «мёртвая рука», уведомление о взломе в 19:41, переписка с Воронцовым. Конверт 4: записка с паролем к облаку | J8: Облако и архив; что знал о взломе ещё при жизни Воронцова; что звонил в полицию он | K8: Технически подкованного или самого скрытного | L8: Речевая привычка выбрана: «Было бы за что». Как пишет в мессенджере (скрины). Голос для звонка | M8: мой дядя | N8: Горенков Александр Сергеевич | O8: 56 | P8: речевую привычку можно взять: после "спасибо", часто отвечает: "было бы за что" (эту возможно не угадают быстро); также все знают такие фразы: вахуе (сильный шок), когда его переспрашивают и говорят "а?", он отвечает "лимон" | R8: фото пришлю как и для всех остальных | W8: Возраст: в жизни 48 | X8: Готово. Отец Марины по сюжету — фамилию оставил. Речевая привычка ВЫБРАНА: «Было бы за что» (ответ на «спасибо») — уже в звонке и опросе. Нужны скрины его сообщений. Голос для звонка запишем позже. | Y8: Горенков Александр Сергеевич
A9: 6 | B9: Стас Лёвин | C9: Актёр (Звездич). Честный свидетель ссоры — точка опоры для игроков | D9: Второстепенный | E9: Любой; любой | F9: Болтливый, любит драму, но не врёт | G9: На сцене — подтверждено | H9: Слышал ссору через стену: «Тебе нужны только площади и деньги» — «Ты заигрался в моралиста, Ваня» — «Думаешь, я не знаю, что ты пытался сделать?»; «Ваня с этим своим баллончиком вечно прятался» | I9: — | J9: Ничего | K9: Самого разговорчивого, любителя пересказывать | L9: Фирменные фразы и манера пересказа — его опрос самый длинный и живой | M9: брат моей тети | N9: Лёвин Сергей Николаевич | O9: 44 | W9: Возраст: в жизни 39 | X9: Тарасовых в деле было 4 → фамилия роли. Имя и отчество — настоящие. 1–3 фразы и как рассказывает истории (у него самый длинный опрос). | Y9: Тарасов Сергей Николаевич
A10: 7 | B10: Светлана Резникова | C10: Помощник режиссёра, ведёт журнал спектакля | D10: Второстепенный | E10: Любой; любой | F10: Педантичная, нервная, всё записывает | G10: За кулисами — подтверждено | H10: «Все были не в форме»; «Иван выходил не с той интонацией, во втором акте задыхался» | I10: Этап 3: в 20:25 видела, как он запивал таблетку, «руки тряслись после разговора с Юрием Викторовичем» | J10: Ничего — просто не придала значения | K10: =+M6+K10+K10:K11+K10+M6+K10+M6+K10 | L10: Манера речи. Стиль коротких пометок для журнала помрежа | M10: мама моя | N10: Резникова Наталья Сергеевна | O10: 47 | Q10: работает учителем в школе, можно взять базовую манеру как у учителей (стиль коротких пометок, я скину тебе фото (не забудь потом попросить только) | W10: Возраст: в жизни 51 | X10: Фамилия Молдованова совпала бы с Воронцовым (игроки решат — жена) → фамилия роли. Исправил «Срегеевна». Фото маминых коротких пометок (тетрадь, записка, список) — для журнала помрежа. | Y10: Молдованова Наталья Срегеевна
A11: 8 | B11: Елена Гнедич | C11: Костюмер | D11: Второстепенный | E11: Любой; любой | F11: Ворчливая: «я не вахтёр» | G11: В костюмерке с двумя монтировщиками — подтверждено | H11: «Кто-то всё время бегал — рабочие, пресса, свои. Я не вахтёр» | I11: Этап 4: видела Волкова у гримёрки №4 в 21:08, «он шёл оттуда» | J11: Что видела Волкова — не хотела наговаривать на «хорошего мальчика» | K11: Главного ворчуна семьи | L11: Ворчливые фразы | M11: бабушка | N11: Гнедич Галина Отчество? | O11: 63 | W11: Возраст: в жизни 68 | X11: Нужно отчество бабушки. Тарасовых было 4 → фамилия роли. 1–3 ворчливые фразы бабушки. | Y11: Тарасова Галина ..
A12: 9 | B12: Виктор «Мастер» | C12: Осветитель. Его лог пульта даёт точное время остановки спектакля | D12: Второстепенный | E12: Любой; любой | F12: Немногословный профи | G12: В световой будке — подтверждено логом пульта | H12: «Стоял у пульта, ничего подозрительного» | I12: Этап 2: лог пульта — аварийная остановка в 21:02:31 | J12: Ничего | K12: Молчаливого «технаря» | L12: 1–2 фирменные фразы | M12: двоюродный брат | N12: Кузнецов Антон Александрович | O12: 50 | W12: Возраст: в жизни 25 | X12: Горенков Антон Александрович выглядел бы сыном Кирилла → фамилия роли. 1–2 фразы. | Y12: Горенков Антон Александрович
A13: 10 | B13: Олег Петрович | C13: Охранник служебного входа | D13: Второстепенный | E13: Любой; старше | F13: Упрямый, добродушный, боится увольнения | G13: Курил 19:35–19:50 — видно на внешней камере | H13: «Муха не пролетела, весь вечер на посту» | I13: Этап 2: после кадров камеры признаёт перекур, просит не говорить начальству | J13: Перекур | K13: Упёртого, но добродушного | L13: Фото «с камеры»: 6–8 кадров у двери с сигаретой (можно бутафорской) | M13: мужчина моей мамы | N13: Лемонов Алексей Отчество? | O13: 64 | X13: Нужно отчество. 1–2 фразы. | Y13: Лемонов Алексей
A14: 11 | B14: Инна | C14: Буфетчица. Ложный след | D14: Второстепенный | E14: Любой; любой | F14: Суетливая, невнимательная, любит красивое | G14: «Носила чай по гримёркам» — свидетелей нет | H14: Забирала чашки, «всё как обычно» | I14: Этап 2: пропажи из костюмерки (брошь, шаль, перчатки) и фото в броши в её соцсети | J14: Ворует из костюмерки | K14: Суетливого, вечно куда-то спешащего | L14: Фото в броши для соцсети. Стиль подписей к постам | M14: мама мужа моей сестры | N14: Рябова Светлана Отчество? | O14: 29 | R14: стиль подписи в соцсетях скину скрином - попроси только | X14: Нужно отчество. Авдеенко оставил майору (иначе Инна и майор — «семья»). Скрин подписей к постам в соцсети. | Y14: Авдеенко Светлана
A15: 12 | B15: Дмитрий | C15: Водитель Воронцова | D15: Второстепенный | E15: Любой; любой | F15: Простой, преданный Воронцову | G15: В машине у служебного входа — видно на внешней камере | H15: «Сказал: жди у заднего входа в 22:00, ни секундой позже, мотор не глуши» | I15: Этап 3: признаёт чемодан и вокзал; молчал, потому что Воронцов просил | J15: Побег Воронцова | K15: Надёжного, немногословного | L15: Фирменные фразы | M15: жена брата моей тети | N15: Горохова Ксения Отчество? | O15: 40 | W15: Возраст: в жизни 40 | X15: Нужно отчество. Тарасовых было 4 → фамилия роли. Роль женская — водитель Ксения. 1–2 фразы. | Y15: Тарасова Ксения
A16: 13 | B16: Софья Вольская | C16: Меценат. Ложный след, ведущий к аукционам | D16: Второстепенный | E16: Любой; 40+ | F16: Светская, уверенная, привыкла получать своё | G16: В ложе №2 с подругой — подтверждено | H16: «Хотела поговорить по личному делу», искала его в 18:20, не поймала | I16: Этап 4: переписка с Воронцовым, письмо эксперта о подделке, строка в реестре облака | J16: Купила на «Закрытом вечере» поддельную табакерку за 2,4 млн ₽ | K16: Самого элегантного и светского | L16: Как пишет в мессенджере (переписка с Воронцовым) | M16: моя тетя | N16: Вольская Светлана Николаевна | O16: 54 | R16: скину фото | W16: Возраст: в жизни 46 | X16: Горенкова выглядела бы женой Кирилла → фамилия роли. Скрины её сообщений. | Y16: Горенкова Светлана Николаевна
A17: 14 | B17: Михаил Громов | C17: Чиновник. Ложный след | D17: Второстепенный | E17: Любой; 45+ | F17: Хамоватый: «Вы знаете, кто я?» | G17: В ложе №1 с охраной — подтверждено | H17: Хамит, требует «не портить имидж культурной столицы»; почему уходил — «не ваше дело» | I17: Бонусные вопросы: пост «на совещании в Северогорске» в 19:30, справка пресс-службы | J17: Прогулял официальное совещание ради премьеры | K17: Самого громкого, любящего покомандовать | L17: Фото «на совещании». Стиль официальных постов | M17: моя сестра | N17: Громова Юлия Сергеевна | O17: 57 | P17: чулида (называет так странного (неопрятного можетет быть) человека): "ну ты и чулида" | R17: скину фото -попроси только | S17: привыкла накручивать волосы рукой | T17: однажды пролила на стол вино, все испачкала и после этого сказала фразу "ну главное не в салат"; эту фразу часто вспоминают, когда что-то пачкают | W17: Возраст: в жизни 28 | X17: Блинова совпала бы с Волковым → фамилия роли. Фразы уже в тексте («чулида», «главное не в салат»). Скрины — когда будут. | Y17: Блинова Юлия Сергеевна
A18: 15 | B18: Сержант Ковалёв | C18: Автор рапорта о Громове | D18: Служебный | E18: Любой; любой | F18: Старательный, канцелярский язык | G18: — | H18: — | I18: — | J18: — | K18: Неиграющего родственника или кого угодно | L18: Только ФИО | M18: отчим мужа моей сестры (можешь поставить на любого из служебных) | N18: Авдеенко Михаил | P18: не пьет, но постоянно шутит, что надо бы всем налить, что он уже напился, почему стаканы пустые и тп | X18: Служебная роль — оставлю вымышленное имя. Михаила Авдеенко предлагаю поставить майором Беляевым (строка ниже). | Y18: Авдеенко Михаил
A19: 16 | B19: Судмедэксперт | C19: Автор заключения и экспертиз | D19: Служебный | E19: Любой; любой | F19: Сухой, педантичный | G19: — | H19: — | I19: Автор экспертиз этапов 2–4 | J19: — | K19: Неиграющего родственника или кого угодно | L19: Только ФИО | M19: поставь любое имя | X19: Оставлю вымышленное имя (Лисицына Наталья Викторовна).
A20: 17 | B20: Майор Беляев | C20: Руководитель. Рассказчик: вводные письма к каждому этапу | D20: Служебный | E20: Любой; любой | F20: Строгий, ироничный | G20: — | H20: — | I20: Пишет вводные к этапам | J20: — | K20: Тебя — ты знаешь разгадку и не играешь | L20: ФИО. Можно фирменные фразы для вводных писем | M20: я лучше буду жертвой (не хочу никого убивать) | N20: Авдеенко Михаил Отчество? | X20: Предлагаю отчима мужа сестры: майор пишет вводные письма к этапам, его шутки «надо бы всем налить» туда лягут. Нужно отчество.
B22: Ролей заполнено: | C22: =COUNTA(M4:M20)&" из "&ROWS(M4:M20)
B23: Ключевых заполнено: | C23: =COUNTIFS(D4:D20,"Ключевой",M4:M20,"<>")&" из "&COUNTIF(D4:D20,"Ключевой")

Sheet Участие
A1: Роль | B1: Родственник | C1: Портрет | D1: Фото в образе или сцене | E1: Видео | F1: Голос (аудио) | G1: Первый опрос | H1: Повторный опрос | I1: Переписка или чат | J1: Соцсеть | K1: Задач
A2: Иван Воронцов | B2: =IF(Персонажи!M4="","— не назначен",Персонажи!M4) | C2: ● | D2: Арбенин; у кассы вокзала | I2: С Кириллом, Вольской, Завьяловым; письмо Марине | K2: =COUNTA(C2:J2)
A3: Юрий Завьялов | B3: =IF(Персонажи!M5="","— не назначен",Персонажи!M5) | C3: ● | D3: Свой кабинет (вещи на столе) | G3: ● | I3: Рабочий чат; ультиматум | K3: =COUNTA(C3:J3)
A4: Артём Волков | B4: =IF(Персонажи!M6="","— не назначен",Персонажи!M6) | C4: ● | D4: Вокзал, у колонны | E4: Монолог 40–60 с | G4: ● | H4: Признание (развязка) | I4: Рабочий чат | K4: =COUNTA(C4:J4)
A5: Марина Тарасова | B5: =IF(Персонажи!M7="","— не назначен",Персонажи!M7) | C5: ● | G5: ● | H5: Этапы 2 и 4 | K5: =COUNTA(C5:J5)
A6: Кирилл | B6: =IF(Персонажи!M8="","— не назначен",Персонажи!M8) | C6: ● | F6: Анонимный звонок (или другой голос) | G6: ● | H6: Этап 3 | I6: С Воронцовым | K6: =COUNTA(C6:J6)
A7: Стас Лёвин | B7: =IF(Персонажи!M9="","— не назначен",Персонажи!M9) | C7: ● | G7: ● | K7: =COUNTA(C7:J7)
A8: Светлана Резникова | B8: =IF(Персонажи!M10="","— не назначен",Персонажи!M10) | C8: ● | G8: ● | H8: Этап 3 | K8: =COUNTA(C8:J8)
A9: Елена Гнедич | B9: =IF(Персонажи!M11="","— не назначен",Персонажи!M11) | C9: ● | G9: ● | H9: Этап 4 | K9: =COUNTA(C9:J9)
A10: Виктор «Мастер» | B10: =IF(Персонажи!M12="","— не назначен",Персонажи!M12) | C10: ● | G10: ● | K10: =COUNTA(C10:J10)
A11: Олег Петрович | B11: =IF(Персонажи!M13="","— не назначен",Персонажи!M13) | C11: ● | D11: Кадры камеры у двери | G11: ● | H11: Этап 2 | K11: =COUNTA(C11:J11)
A12: Инна | B12: =IF(Персонажи!M14="","— не назначен",Персонажи!M14) | C12: ● | D12: В броши | G12: ● | J12: Профиль, 6–8 постов | K12: =COUNTA(C12:J12)
A13: Дмитрий | B13: =IF(Персонажи!M15="","— не назначен",Персонажи!M15) | C13: ● | D13: За рулём (кадры камеры) | G13: ● | H13: Этап 3 | K13: =COUNTA(C13:J13)
A14: Софья Вольская | B14: =IF(Персонажи!M16="","— не назначен",Персонажи!M16) | C14: ● | G14: ● | I14: С Воронцовым | K14: =COUNTA(C14:J14)
A15: Михаил Громов | B15: =IF(Персонажи!M17="","— не назначен",Персонажи!M17) | C15: ● | D15: На «совещании» | G15: ● | J15: Профиль, 8–10 постов | K15: =COUNTA(C15:J15)
A16: Сержант Ковалёв | B16: =IF(Персонажи!M18="","— не назначен",Персонажи!M18) | K16: =COUNTA(C16:J16)
A17: Судмедэксперт | B17: =IF(Персонажи!M19="","— не назначен",Персонажи!M19) | K17: =COUNTA(C17:J17)
A18: Майор Беляев | B18: =IF(Персонажи!M20="","— не назначен",Персонажи!M20) | K18: =COUNTA(C18:J18)
A19: Всего | C19: =COUNTA(C2:C18) | D19: =COUNTA(D2:D18) | E19: =COUNTA(E2:E18) | F19: =COUNTA(F2:F18) | G19: =COUNTA(G2:G18) | H19: =COUNTA(H2:H18) | I19: =COUNTA(I2:I18) | J19: =COUNTA(J2:J18) | K19: =SUM(K2:K18)
A21: ● — нужно обязательно. Текст в ячейке — что именно. Опросы пишу я по фразам из листа «Персонажи», от родственника нужны только фразы и манера.

Sheet Фоновые имена
A1: Кто | B1: Где упоминается | C1: Имя (заполни) | D1: Можно родственника? | E1: Подсказка
A2: Исполнительница роли Нины | B2: Программка «Маскарада» (1-07) | D2: Да | E2: Пустые строки я заполню вымышленными именами — это нормально. Вписывай только тех, кого хочешь увидеть в деле.
A3: Подруга Вольской в ложе №2 | B3: Алиби Вольской, её опрос | D3: Да
A4: Монтировщик 1 | B4: Алиби Гнедич | D4: Да
A5: Монтировщик 2 | B5: Алиби Гнедич | D5: Да
A6: Сестра Марины | B6: Вторая дочь Кирилла. Алиби Марины (телефонный разговор). Только ИМЯ — фамилия и отчество от Кирилла | D6: Да
A7: Врач скорой | B7: Карта вызова (1-03) | D7: Да
A8: Завхоз театра | B8: Адресат записки о камере (4-05) | D8: Да
A9: Пресс-секретарь Громова | B9: Справка пресс-службы (2-10) | D9: Да
A10: Г. Родионов, директор ООО «Сценическая мастерская» | B10: Выписка по ООО (4-03) | D10: Лучше вымышленное
A11: Брат Родионова, кредитор Волкова | B11: Выписка по ООО (4-03) | D11: Лучше вымышленное
A12: Эксперт, оценивший табакерку | B12: Письмо эксперта (4-11) | D12: Да
A13: Охранник Громова | B13: Алиби Громова, рапорт | D13: Да
A14: Администратор зала | B14: Вызвала скорую (рапорт 1-02, карта 1-03) | D14: Да
... A16: Заведующий постановочной частью | B16: Подписал смету декораций (4-02) | D16: Да

Sheet Таймлайн
A1: Когда | B1: Что произошло | C1: Какой след остался
A2: Сентябрь 2026 | B2: Ультиматум Воронцова Завьялову. Воронцов проговаривается про ежедневное подтверждение страховки | C2: Переписка в облаке
A3: ~15 октября | B3: Эксперт сообщает Вольской, что табакерка — подделка | C3: Письмо эксперта 4-11
A4: 20 октября | B4: Вольская пишет Воронцову. Он отвечает «Поговорим после премьеры» | C4: Переписка 4-12
A5: ~20 октября | B5: Кирилл настраивает облако и «мёртвую руку», отключает восстановление по SMS | C5: Переписка Кирилла и Воронцова
A6: Конец октября | B6: На репетиции Воронцов подтверждает страховку с телефона, Волков подсматривает пароль | C6: Переписка 4 ноября
A7: 30 октября, 14:37 | B7: Воронцов покупает билет в кассе №2 за наличные. Волков, следящий за ним, стоит у колонны | C7: Билет 3-07, вокзальная камера 4-08
A8: 3 ноября | B8: Завьялов запрещает чинить камеру в коридоре гримёрок; оплата договора с ООО «Сценическая мастерская» | C8: Записка 4-05, договор 4-02
A9: 4 ноября | B9: Кирилл: «Ты вводил пароль при людях на репетиции, смени». Воронцов меняет пароль | C9: Переписка в 3-03
A10: 7 ноября | B10: Завьялов ставит Волкова «дежурить» на 3-м этаже во время премьеры | C10: Рабочий чат 4-06
A11: 8 ноября, 14:12 | B11: Волков записывает видео «репетиции» днём | C11: Метаданные, дневной свет
A12: 8 ноября | B12: Завьялов покупает Анаприлин на 2 недели раньше обычного | C12: Аптечная выписка 4-04
... A41: 12.11, утро | B41: Игроки получают материалы проверки | C41: Вводное письмо 1-01
